{
  "creds": {
    "noiseKey": {
      "private": {
        "type": "Buffer",
        "data": "yG6wMbdUcZzH7nKot1MH8y5sfgKomB+1g/h/cef7Vl0="
      },
      "public": {
        "type": "Buffer",
        "data": "RIOMzEuINPl4ahxl3UBwFig+WKU9T2V5fo+1/3OlHEQ="
      }
    },
    "signedIdentityKey": {
      "private": {
        "type": "Buffer",
        "data": "2DnCjCyWKvpi0L7siTkFw2EWoIO+o8HlZQDwuyZge3I="
      },
      "public": {
        "type": "Buffer",
        "data": "SgFdMZoZajaDBSo7QZquTyEskQZFpTak6uNJPfxUdkU="
      }
    },
    "signedPreKey": {
      "keyPair": {
        "private": {
          "type": "Buffer",
          "data": "ULz1TkDzE8MEGHmcCdFLx1rzd2DmRs8oFJBKATSirUA="
        },
        "public": {
          "type": "Buffer",
          "data": "18NUD9sfhRDFfbeGOz8MlAMPRwtnbUKanGP0oMvut34="
        }
      },
      "signature": {
        "type": "Buffer",
        "data": "s4xFa9THSpE2UxG8wpJFFlbI59ZqxgdybOK9VtXKxd5WhTtRyprej2xsl6X82M6Hhu3PnCDhaR0tDV2eiYyChw=="
      },
      "keyId": 1
    },
    "registrationId": 218,
    "advSecretKey": "AcS95RB0g8wwOAMaxJC5utXAbjpv5IiH9Xqfvt1/gzo=",
    "processedHistoryMessages": [
      {
        "key": {
          "remoteJid": "4915678244172@s.whatsapp.net",
          "fromMe": true,
          "id": "CC5FF6623F327DD37400730B5D9C8928"
        },
        "messageTimestamp": 1661873871
      },
      {
        "key": {
          "remoteJid": "4915678244172@s.whatsapp.net",
          "fromMe": true,
          "id": "0B2CD1E44C03162801F1A2711210EABE"
        },
        "messageTimestamp": 1661873871
      },
      {
        "key": {
          "remoteJid": "4915678244172@s.whatsapp.net",
          "fromMe": true,
          "id": "58F368F8546160A981F979DC5C33B44E"
        },
        "messageTimestamp": 1661873877
      }
    ],
    "nextPreKeyId": 31,
    "firstUnuploadedPreKeyId": 31,
    "accountSettings": {
      "unarchiveChats": false
    },
    "account": {
      "details": "CLXwmuQBEMnduJgGGAI=",
      "accountSignatureKey": "0PThX+T8FDZWqe45456crUdsFbpUOszNOCgPozrzRUc=",
      "accountSignature": "PY5cn0sO4CY2BEomFdoP7BbY63JlxH80154Rfn8AyUg2t3S0gDTJ/InRybcO8XV8f1MWkqT4HvpsHxzOkUGqAg==",
      "deviceSignature": "F7psddQEcYJT2jiGHq/jF5yAEharjoIJ9HNaNgCFDZIsn2jyfJgEaKUWWGfbX1P8kGHPHw7kN4fLPgsm/IS+gg=="
    },
    "me": {
      "id": "4915678244172:15@s.whatsapp.net",
      "name": "Umbrella ☔ Bot"
    },
    "signalIdentities": [
      {
        "identifier": {
          "name": "4915678244172:15@s.whatsapp.net",
          "deviceId": 0
        },
        "identifierKey": {
          "type": "Buffer",
          "data": "BdD04V/k/BQ2VqnuOeOenK1HbBW6VDrMzTgoD6M680VH"
        }
      }
    ],
    "platform": "android",
    "lastAccountSyncTimestamp": 1661873941,
    "myAppStateKeyId": "AAAAACDc"
  },
  "keys": {
    "preKeys": {
      "1": null,
      "2": {
        "private": {
          "type": "Buffer",
          "data": "OAomW+ZpTo0dTmMnk/aO32koKrVNpybsvwUjPDG7VnY="
        },
        "public": {
          "type": "Buffer",
          "data": "b24NaVIXXZ5TuCrIxCYiUYNfTn4chj/PtB7avHFW/F8="
        }
      },
      "3": {
        "private": {
          "type": "Buffer",
          "data": "GDNr8wdkqZ/erJMugaaTfAqgf4S/eU5hSsDI50Lw+FU="
        },
        "public": {
          "type": "Buffer",
          "data": "1HbNzaQBlsReUKPv5qcSCjEhU461AJjq+srubLuLizg="
        }
      },
      "4": {
        "private": {
          "type": "Buffer",
          "data": "iKkM1VD0QgmjOkzr8+tonAvXOEwA0LnrdHEwn5OnY0I="
        },
        "public": {
          "type": "Buffer",
          "data": "8Oqx4UlErNxqDUOBqbq/hxgQXGTCO+BM5xoao1T1wnA="
        }
      },
      "5": {
        "private": {
          "type": "Buffer",
          "data": "4PKxPiAZaKe7upOGwP54WU1dMx8+Oi08xFJ0cGDIuHc="
        },
        "public": {
          "type": "Buffer",
          "data": "7Y62UdQrl7x5PMVFMuvE7raTftVszLtVdvC6uxqAVWk="
        }
      },
      "6": {
        "private": {
          "type": "Buffer",
          "data": "WIKfanqZJhRD7J/wv0a+cDbNhavQ3PD9lH8FPqHUnUQ="
        },
        "public": {
          "type": "Buffer",
          "data": "xuy8KdAHgzfufLvQbENkf0WnRfx45k6Rri90lf0blSU="
        }
      },
      "7": {
        "private": {
          "type": "Buffer",
          "data": "MDF5joQVKzgFawmG6N2/nJj/ycySq3/otRtW26BlUnM="
        },
        "public": {
          "type": "Buffer",
          "data": "mYpptqZFSzoKniF6qGW88zEO9qHVV62mCXo1s72RMwk="
        }
      },
      "8": {
        "private": {
          "type": "Buffer",
          "data": "iIEjwX7MLS8z+av084kFBDeDO2Olu7ekyO3/GvvauGE="
        },
        "public": {
          "type": "Buffer",
          "data": "rarkat3LN8ZrgiyWz/yRru9UoddwEBrP39DxhTVBuXI="
        }
      },
      "9": {
        "private": {
          "type": "Buffer",
          "data": "GGShiinCB7XOEqmROE/KiyS19qQLxEqY6rCgEuJ5DFo="
        },
        "public": {
          "type": "Buffer",
          "data": "Ybh5Zl5RtC0gZwvXyvMS+nKVV7LGs7p1xdbcKPm35wg="
        }
      },
      "10": {
        "private": {
          "type": "Buffer",
          "data": "oFXHG9LYcsG7J0A+XPAGUnedFCKugTi0Ce8LFoAiyHg="
        },
        "public": {
          "type": "Buffer",
          "data": "eNpEBNZO1Fl3BlwPqP0xHnDgmICac5gFvJfJvU64OgA="
        }
      },
      "11": null,
      "12": {
        "private": {
          "type": "Buffer",
          "data": "uDP77eHKRso4OrYasHpia5aH6/2XXeRg1ECBpkrGtl8="
        },
        "public": {
          "type": "Buffer",
          "data": "KzV0OO0/HoUgjMpJr0HmGj7EOFL2Ya6DL+O34wzwNk0="
        }
      },
      "13": {
        "private": {
          "type": "Buffer",
          "data": "sKgZCrw1EOUQ5P092yG+IsV9EPa3f2YhcBrQ89uHC0A="
        },
        "public": {
          "type": "Buffer",
          "data": "SsOu7+7C4FnRPd9R0Tftuuk7qUNHhv+20okDtDN5oAE="
        }
      },
      "14": null,
      "15": {
        "private": {
          "type": "Buffer",
          "data": "eBwdYm6WXtC5ylQFZrw1YhnfpimYbGI78g8qq/6rnFc="
        },
        "public": {
          "type": "Buffer",
          "data": "xmGumsAAsSRpyfaHtDLXUnyB1qFN4W3yilFrxASuDEk="
        }
      },
      "16": {
        "private": {
          "type": "Buffer",
          "data": "mFKu2V96z6ofphN6b1R045OgB2Z+xaTjOaAFl5C1xFE="
        },
        "public": {
          "type": "Buffer",
          "data": "jQ3mTv3T/UQBfJYMVPA4ARNL1IxN55Oj0nllNo/N404="
        }
      },
      "17": {
        "private": {
          "type": "Buffer",
          "data": "6L0RjeWO80alPY3vu0c7Lj3Gchw5tNqAKZ+8UBBHnG4="
        },
        "public": {
          "type": "Buffer",
          "data": "eAts/NJWt3CUv4OzFae+9JjzZtO7P9X+bV6eRL/EGT4="
        }
      },
      "18": {
        "private": {
          "type": "Buffer",
          "data": "SDpTRmVL7j1WyDfpsDYQX9a1pNbVICmTL/kY2ryGiHM="
        },
        "public": {
          "type": "Buffer",
          "data": "wxH87PKcQZ3VtW6i9rkElCrB9P1ys1wRIQBL8dTwzi4="
        }
      },
      "19": {
        "private": {
          "type": "Buffer",
          "data": "sOlQCXr/0/VO4DJRNxAUyjoDEXzlIVXz3mqzBKmLzkM="
        },
        "public": {
          "type": "Buffer",
          "data": "vSsqBZ9BmmP0R0+H5WrjQkQfAmrmzhwEtCbxJ0wfTHY="
        }
      },
      "20": {
        "private": {
          "type": "Buffer",
          "data": "qN0jnrmmlildtQMdGhmsnzCt9DwHGH2OREGgN7nr7EA="
        },
        "public": {
          "type": "Buffer",
          "data": "DOM+NsAkfgulbv3VeMrEXjJUnasoK3TlfpEBJwTIbk0="
        }
      },
      "21": {
        "private": {
          "type": "Buffer",
          "data": "iMhsp0lcHJokdyU9fto6OVzHbpU5kNI8gmIiEIdCY2w="
        },
        "public": {
          "type": "Buffer",
          "data": "iRVZYWIlyZUd+phzsf/JVrt2f0lFHVRST/n3H6NT7kM="
        }
      },
      "22": {
        "private": {
          "type": "Buffer",
          "data": "EDdl5IoC/Hrr+MwisFN3muGpUG+RYoUUfAcI4+mb5Xw="
        },
        "public": {
          "type": "Buffer",
          "data": "4LxNDrRh/FMc7GNZH9Jk5jAKyHgXrZqu+dWHkg3E810="
        }
      },
      "23": {
        "private": {
          "type": "Buffer",
          "data": "2KV17c8+bn0AWSz5zSbyKiWfQ+kVum/EoKypQl6EDF4="
        },
        "public": {
          "type": "Buffer",
          "data": "kWuo0+Ijdd5++A6fm1Y/W74THdV+SrFLnzJq7+wIqRo="
        }
      },
      "24": {
        "private": {
          "type": "Buffer",
          "data": "UE3yAIoLr9w4dqfuqIoRPI3U7MQicwHdUZ/IJxV1J2w="
        },
        "public": {
          "type": "Buffer",
          "data": "4+84e2fCtSpY1w1gw/QxktYHCDXU0LZ300uItmtlO0I="
        }
      },
      "25": {
        "private": {
          "type": "Buffer",
          "data": "YPnJPYr1DLFaBsCULcWfWN0XKKqhcQB2i8ZkeyY4DkA="
        },
        "public": {
          "type": "Buffer",
          "data": "bZMlr2gbFHwh0yEIArkoiJrHF0MU/PPTfHYYg8SRFTM="
        }
      },
      "26": {
        "private": {
          "type": "Buffer",
          "data": "4F5EbglCO48ZivMCJgwSCXe8S/wLeDGWggi97qnDVFU="
        },
        "public": {
          "type": "Buffer",
          "data": "raL1J/aTbtGN1aZs9bQq4DRinDmdvRjRII8VI+elUBA="
        }
      },
      "27": {
        "private": {
          "type": "Buffer",
          "data": "cKWLUHNxXiTvCGJphVyU1UCRd8IC6hYOcNeMvOttVno="
        },
        "public": {
          "type": "Buffer",
          "data": "lrtdlUE7EuMdrz57OeUVnmnR8944DOik2IaqojoVVWo="
        }
      },
      "28": {
        "private": {
          "type": "Buffer",
          "data": "EP54uQqIwHT466FvHmNT8KSULRepVQwZgFlgI5Zc32c="
        },
        "public": {
          "type": "Buffer",
          "data": "+E+3sHkLKexZNVArJp6n+gSDZIEZjzhO3C881pjCuk0="
        }
      },
      "29": {
        "private": {
          "type": "Buffer",
          "data": "EHv4vFRlX8dIsH+xL9DthmK7elys91O6Z123F/cYhUc="
        },
        "public": {
          "type": "Buffer",
          "data": "3APlBwOPNOPDLnssIvT8SeavogbYiPikejS5XuLG0S8="
        }
      },
      "30": {
        "private": {
          "type": "Buffer",
          "data": "GBlknwbl49KEEDnRk9UKi1yCuaDoCF1S6XkWXlXcgkc="
        },
        "public": {
          "type": "Buffer",
          "data": "8S1FUfYxHYFNuIY6aMifmcwlS6UFTaBRVkjSY2r16wI="
        }
      }
    },
    "sessions": {
      "4915678244172.0": {
        "_sessions": {
          "BawDho9y0T7CYC5nWrgKg7hxQHIPmX5JxKWHJ2I9jmFL": {
            "registrationId": 2093897010,
            "currentRatchet": {
              "ephemeralKeyPair": {
                "pubKey": "BVTJsf4FTeL0pqk2yv0syBLlmp35UgzX8BBZbtEMPL1x",
                "privKey": "wHI/YNJkQAlipJBX4TqfexyVCojsUmFxJJH9gGxGVEo="
              },
              "lastRemoteEphemeralKey": "BfFxYNdbB0MVaRyEcxV8yyWPnuQEnFSZNp1efcsCGsAQ",
              "previousCounter": 9,
              "rootKey": "QpVrW9XuX9MsjwzLWdNpE6FIfzYHqZKH5N/lgH0/3yw="
            },
            "indexInfo": {
              "baseKey": "BawDho9y0T7CYC5nWrgKg7hxQHIPmX5JxKWHJ2I9jmFL",
              "baseKeyType": 2,
              "closed": 1661873817255,
              "used": 1661873805509,
              "created": 1661873798075,
              "remoteIdentityKey": "BdD04V/k/BQ2VqnuOeOenK1HbBW6VDrMzTgoD6M680VH"
            },
            "_chains": {
              "BWK3qNNAxADMtyJthGq5Eyc6XE1CvlKjQVPO8Vi9TnkT": {
                "chainKey": {
                  "counter": 4
                },
                "chainType": 2,
                "messageKeys": {}
              },
              "BfFxYNdbB0MVaRyEcxV8yyWPnuQEnFSZNp1efcsCGsAQ": {
                "chainKey": {
                  "counter": 0,
                  "key": "SX+QjTFmNoMXl5fp8vGkMeqBU0ZGQaM57EiyXutWXTE="
                },
                "chainType": 2,
                "messageKeys": {}
              },
              "BVTJsf4FTeL0pqk2yv0syBLlmp35UgzX8BBZbtEMPL1x": {
                "chainKey": {
                  "counter": 1,
                  "key": "+aEU8duk6GBkPQ2RLvdEuxMXv4v9QwyeCixOoDD/3DM="
                },
                "chainType": 1,
                "messageKeys": {}
              }
            }
          },
          "Bc3dN1MZ6gxC8flmW3QFKfD4/fa1pfjNf0EGCU0uLu5n": {
            "registrationId": 2093897010,
            "currentRatchet": {
              "ephemeralKeyPair": {
                "pubKey": "BUfMsEeHOUqKMrXKKTp3GbsGen7zfrW00utRfuMkLq8M",
                "privKey": "ONThqUhyFJf4F+9z6HrTDeTUU0nHWtAX2Fj40+vrzE4="
              },
              "lastRemoteEphemeralKey": "BWLf7/5Amv/s3IvCgK4BU159ZhXLK8l9L94Dnz/Pp91t",
              "previousCounter": 0,
              "rootKey": "w2OFSlJ3y/noCU8FzzS1SjumOK0g7gfLOCw+XTXgSsU="
            },
            "indexInfo": {
              "baseKey": "Bc3dN1MZ6gxC8flmW3QFKfD4/fa1pfjNf0EGCU0uLu5n",
              "baseKeyType": 1,
              "closed": -1,
              "used": 1661873817253,
              "created": 1661873817252,
              "remoteIdentityKey": "BdD04V/k/BQ2VqnuOeOenK1HbBW6VDrMzTgoD6M680VH"
            },
            "_chains": {
              "BUfMsEeHOUqKMrXKKTp3GbsGen7zfrW00utRfuMkLq8M": {
                "chainKey": {
                  "counter": 0,
                  "key": "eXGjy5L479doIBsnEEUOstLE5tIOgtvEOX6cgwJPRgQ="
                },
                "chainType": 1,
                "messageKeys": {}
              }
            },
            "pendingPreKey": {
              "signedKeyId": 1,
              "baseKey": "Bc3dN1MZ6gxC8flmW3QFKfD4/fa1pfjNf0EGCU0uLu5n",
              "preKeyId": 14056767
            }
          }
        },
        "version": "v1"
      },
      "4915678244172:14.0": {
        "_sessions": {
          "BRyMevCiDZReZAPlrwpG/9s423vyesK4XzSg8JGsfJtl": {
            "registrationId": 100,
            "currentRatchet": {
              "ephemeralKeyPair": {
                "pubKey": "BaQP06mReVvrHOwFbP7qnUbIDlGJaKbTXknyAEkkTnF4",
                "privKey": "yAFoZSj+uXBrPVS6aht9ZGEvWN01gF+BwW7D4qBR/10="
              },
              "lastRemoteEphemeralKey": "BSxiU0jB7Oh1hUBz5HGCHFrnoUVrRsrMGxYM21xkEw15",
              "previousCounter": 0,
              "rootKey": "9OAu/zfO3P1hXLKS9Nip4vVQe9CUsTImnX+zclgWGe0="
            },
            "indexInfo": {
              "baseKey": "BRyMevCiDZReZAPlrwpG/9s423vyesK4XzSg8JGsfJtl",
              "baseKeyType": 1,
              "closed": 1661873801294,
              "used": 1661873801278,
              "created": 1661873801278,
              "remoteIdentityKey": "BePhXknNicooPhhN1MrAwQmdQY12g+fMDJaXtlfIxmcb"
            },
            "_chains": {
              "BaQP06mReVvrHOwFbP7qnUbIDlGJaKbTXknyAEkkTnF4": {
                "chainKey": {
                  "counter": 0,
                  "key": "SB13yANWNDQq6hXotKD4nRWu1KkH8ok+DTnwPiV9zQg="
                },
                "chainType": 1,
                "messageKeys": {}
              }
            },
            "pendingPreKey": {
              "signedKeyId": 1,
              "baseKey": "BRyMevCiDZReZAPlrwpG/9s423vyesK4XzSg8JGsfJtl",
              "preKeyId": 21
            }
          },
          "BTfkAi2r2yEZpEmiEwxR9bsdcH6WHa7KbE6JYNsL2Z8b": {
            "registrationId": 100,
            "currentRatchet": {
              "ephemeralKeyPair": {
                "pubKey": "BXoliSe048qsZnp++BqP7zru5ljHZ8hVwfZzQHZNOFJe",
                "privKey": "gFrlAaoutpcLtKBlfgWiok0LAfLT5emT/M1N6fZ2CF0="
              },
              "lastRemoteEphemeralKey": "BSxiU0jB7Oh1hUBz5HGCHFrnoUVrRsrMGxYM21xkEw15",
              "previousCounter": 0,
              "rootKey": "ExHW/GSr8s1Hb/UL1Xqata91QvHddtGklKz197GUB+g="
            },
            "indexInfo": {
              "baseKey": "BTfkAi2r2yEZpEmiEwxR9bsdcH6WHa7KbE6JYNsL2Z8b",
              "baseKeyType": 1,
              "closed": 1661873801418,
              "used": 1661873801291,
              "created": 1661873801291,
              "remoteIdentityKey": "BePhXknNicooPhhN1MrAwQmdQY12g+fMDJaXtlfIxmcb"
            },
            "_chains": {
              "BXoliSe048qsZnp++BqP7zru5ljHZ8hVwfZzQHZNOFJe": {
                "chainKey": {
                  "counter": 0,
                  "key": "LWFHQY57awdVDFuk6OVaPCUSYRpu81rl/knRTWIpib0="
                },
                "chainType": 1,
                "messageKeys": {}
              }
            },
            "pendingPreKey": {
              "signedKeyId": 1,
              "baseKey": "BTfkAi2r2yEZpEmiEwxR9bsdcH6WHa7KbE6JYNsL2Z8b",
              "preKeyId": 1
            }
          },
          "BeFDjUr7fXQxFiwHgaZ7l8ayN18Y8R/2utlJ72AuWFgi": {
            "registrationId": 100,
            "currentRatchet": {
              "ephemeralKeyPair": {
                "pubKey": "Bbe7xV0A8r6/1+gh/gXQsVW+aCBo4dzBB6bXCPa0Wgpe",
                "privKey": "IOH7k15WBUQfCQo9x9SWDCBJi8MHGUJM3G1Siof+j20="
              },
              "lastRemoteEphemeralKey": "BSxiU0jB7Oh1hUBz5HGCHFrnoUVrRsrMGxYM21xkEw15",
              "previousCounter": 0,
              "rootKey": "yRYngr3BJDiW4Qbs8BJCfGb5ECeIx0JgreOcgLHddO0="
            },
            "indexInfo": {
              "baseKey": "BeFDjUr7fXQxFiwHgaZ7l8ayN18Y8R/2utlJ72AuWFgi",
              "baseKeyType": 1,
              "closed": -1,
              "used": 1661873801413,
              "created": 1661873801413,
              "remoteIdentityKey": "BePhXknNicooPhhN1MrAwQmdQY12g+fMDJaXtlfIxmcb"
            },
            "_chains": {
              "Bbe7xV0A8r6/1+gh/gXQsVW+aCBo4dzBB6bXCPa0Wgpe": {
                "chainKey": {
                  "counter": 8,
                  "key": "FJ/U1b6LbC64scMjxtl5c7H4UVVedMtLyvvmrCdV14s="
                },
                "chainType": 1,
                "messageKeys": {}
              }
            },
            "pendingPreKey": {
              "signedKeyId": 1,
              "baseKey": "BeFDjUr7fXQxFiwHgaZ7l8ayN18Y8R/2utlJ72AuWFgi",
              "preKeyId": 20
            }
          }
        },
        "version": "v1"
      },
      "447935699967.0": {
        "_sessions": {
          "BfwcIYBEY98XzC417Bzeyi+KfSiZLf2z5/chjEUVh8Z0": {
            "registrationId": 515651752,
            "currentRatchet": {
              "ephemeralKeyPair": {
                "pubKey": "BdKfr/Pfmga1iFngt+u1JZ6Sul2yHGnZ1AIz4hfWL/Bh",
                "privKey": "8D5GFVik42VDALFBIc9IdGpFqPlXTSsOLp8/C8O6aVk="
              },
              "lastRemoteEphemeralKey": "BcVf6t3sdwyxhCeXEnWkve0vB45z9d2shX+fJHNvaGwz",
              "previousCounter": 0,
              "rootKey": "lGnwCd5MZrJNweGHA6hjflSfAQIA0ch8j5GExTQnaaA="
            },
            "indexInfo": {
              "baseKey": "BfwcIYBEY98XzC417Bzeyi+KfSiZLf2z5/chjEUVh8Z0",
              "baseKeyType": 2,
              "closed": -1,
              "used": 1661873809157,
              "created": 1661873809157,
              "remoteIdentityKey": "BVYl2/00ADxIPBJh8g5xmGIejh8tWNuII8114oefPXY2"
            },
            "_chains": {
              "BcVf6t3sdwyxhCeXEnWkve0vB45z9d2shX+fJHNvaGwz": {
                "chainKey": {
                  "counter": 0,
                  "key": "b3jsjlrb4l3QWG9va2cfJQ1g8V7ocEBsj2rgEvfxh1c="
                },
                "chainType": 2,
                "messageKeys": {}
              },
              "BdKfr/Pfmga1iFngt+u1JZ6Sul2yHGnZ1AIz4hfWL/Bh": {
                "chainKey": {
                  "counter": 1,
                  "key": "EmJjDHOQndaQxuW9MAKxehmd+75lKdyP+EHW4A52HBw="
                },
                "chainType": 1,
                "messageKeys": {}
              }
            }
          }
        },
        "version": "v1"
      },
      "4915256334479.0": {
        "_sessions": {
          "BQlRaeQN2hkRi07REKP19fgEQhR2q+T7taMryaftHCp7": {
            "registrationId": 1155511028,
            "currentRatchet": {
              "ephemeralKeyPair": {
                "pubKey": "BegMGV7tLCatWSpDtrAiQb/r0sDuoHjzv1TYF+6+Eo5v",
                "privKey": "IKIC6/lrw2KyHJoUb2tegjCJrnc8V2NqvXkcoAn9EHw="
              },
              "lastRemoteEphemeralKey": "BYrd5I42YiRs5SkSQ0RcSr24s4WvOa5QdjdSEFgaODFV",
              "previousCounter": 0,
              "rootKey": "/cUuxYLiwz3kChNkQJ+T24yB0lQWb/HfEGIgk+ir6Pc="
            },
            "indexInfo": {
              "baseKey": "BQlRaeQN2hkRi07REKP19fgEQhR2q+T7taMryaftHCp7",
              "baseKeyType": 1,
              "closed": -1,
              "used": 1661873816764,
              "created": 1661873816764,
              "remoteIdentityKey": "BYmSK3QE5pgOJW3jmZlwE1X5mbXxz9ThCW8aI4eNDiEZ"
            },
            "_chains": {
              "BegMGV7tLCatWSpDtrAiQb/r0sDuoHjzv1TYF+6+Eo5v": {
                "chainKey": {
                  "counter": 1,
                  "key": "eRBSZxvRYHbBNUEVg/vGCWy/9YLL9mr5CIaa1KrsCqg="
                },
                "chainType": 1,
                "messageKeys": {}
              }
            },
            "pendingPreKey": {
              "signedKeyId": 7,
              "baseKey": "BQlRaeQN2hkRi07REKP19fgEQhR2q+T7taMryaftHCp7",
              "preKeyId": 14083517
            }
          }
        },
        "version": "v1"
      },
      "4915678444438.0": {
        "_sessions": {
          "BZc9445CYW0ggizvCd+FOz4lMGRAvL9Orw0jYM1IfJF4": {
            "registrationId": 1783378803,
            "currentRatchet": {
              "ephemeralKeyPair": {
                "pubKey": "BTVKiSg3+/CBy8XP3UdF8GeG9kG8wubw1c7Iy3Bc5ykO",
                "privKey": "WGluSl1eYPs7Lw7kQQCGAia7VTXulrAb/q6YbXYkP10="
              },
              "lastRemoteEphemeralKey": "BT41jTlcEfA91XSRffuAWOrxk85SJpXKaK3kuSvfYQU9",
              "previousCounter": 0,
              "rootKey": "Xpehyie4L+k92BnOiJSdJnHN6zMnYYvR7b94D5iVmKg="
            },
            "indexInfo": {
              "baseKey": "BZc9445CYW0ggizvCd+FOz4lMGRAvL9Orw0jYM1IfJF4",
              "baseKeyType": 2,
              "closed": -1,
              "used": 1661873933831,
              "created": 1661873933831,
              "remoteIdentityKey": "BUgWnrI17sydjdV4JeqX0kLLYj3x/NqPrdQqfZ6i7WgH"
            },
            "_chains": {
              "BT41jTlcEfA91XSRffuAWOrxk85SJpXKaK3kuSvfYQU9": {
                "chainKey": {
                  "counter": 0,
                  "key": "84HlDCXzg7FbAHHIDyPP6m1jhr6fna/0K6UPfiBGqhU="
                },
                "chainType": 2,
                "messageKeys": {}
              },
              "BTVKiSg3+/CBy8XP3UdF8GeG9kG8wubw1c7Iy3Bc5ykO": {
                "chainKey": {
                  "counter": -1,
                  "key": "udE0BJ6H+DIiU4pYHXxXvl/kNNXCkVSDUpV4cmCvzOI="
                },
                "chainType": 1,
                "messageKeys": {}
              }
            }
          }
        },
        "version": "v1"
      }
    },
    "appStateSyncKeys": {
      "AAAAACDl": {
        "keyData": "oRkLCbNgpT2JIHXxMu3ucx26lcbce9y9QhHOAiDQpcU=",
        "fingerprint": {
          "rawId": 478591028,
          "currentIndex": 3,
          "deviceIndexes": [
            0,
            1,
            2
          ]
        },
        "timestamp": "1661873117223"
      },
      "AAAAACDm": {
        "keyData": "8lgcMtHYEBERcfDMbVH+jcuQRL02C3DQvKzLDSKIPvY=",
        "fingerprint": {
          "rawId": 478591028,
          "currentIndex": 3,
          "deviceIndexes": [
            0,
            2
          ]
        },
        "timestamp": "1661873119543"
      },
      "AAAAACDk": {
        "keyData": "iojhkGCBCFS1wVaHDsmMkbWdtRRbmr79R+AcFw0eJE4=",
        "fingerprint": {
          "rawId": 478591028,
          "currentIndex": 3,
          "deviceIndexes": [
            0,
            1,
            2,
            3
          ]
        },
        "timestamp": "0"
      },
      "AAAAACDh": {
        "keyData": "sRqKh+44TJIcyXn6iIKAcH4yrnhbabW1tBGHB268+W8=",
        "fingerprint": {
          "rawId": 478591025,
          "currentIndex": 3,
          "deviceIndexes": [
            0,
            1,
            3
          ]
        },
        "timestamp": "1661799930667"
      },
      "AAAAACDi": {
        "keyData": "0Cn2oqoqXDZ/Np5O5tcxqFDHwlpnmzxrZ6wpf1ydCJE=",
        "fingerprint": {
          "rawId": 478591025,
          "currentIndex": 3,
          "deviceIndexes": [
            0,
            1
          ]
        },
        "timestamp": "1661799935006"
      },
      "AAAAACDf": {
        "keyData": "8mCoGNFuWn3CmTy2EZCSiFkO8Uk4Davr3QOt2jVBRZY=",
        "fingerprint": {
          "rawId": 478591024,
          "currentIndex": 1,
          "deviceIndexes": [
            0,
            1
          ]
        },
        "timestamp": "1661794361347"
      },
      "AAAAACDg": {
        "keyData": "EXNKdx44MmmgV9e9hUnqhRWIgwWqfCmib+c2T8AdH2E=",
        "fingerprint": {
          "rawId": 478591025,
          "currentIndex": 2,
          "deviceIndexes": [
            0,
            1,
            2
          ]
        },
        "timestamp": "1661796755474"
      },
      "AAkAACDj": {
        "keyData": "jH2LqUEg3Pl2Nkm6lM/sbHyi9yAQMxXO2kzYVVVKTHU=",
        "fingerprint": {
          "rawId": 478591026,
          "currentIndex": 1,
          "deviceIndexes": [
            0,
            1
          ]
        },
        "timestamp": "0"
      },
      "AAAAACDd": {
        "keyData": "cV5upD3Py0S066yGnunAS/c+tsnkwJ3esZ3971epKdc=",
        "fingerprint": {
          "rawId": 478591022,
          "currentIndex": 3,
          "deviceIndexes": [
            0,
            3
          ]
        },
        "timestamp": "0"
      },
      "AAAAACDe": {
        "keyData": "1rzXzaWK+LmuITDNLIyBkjiLU6LVSloPWD1KAKgmNLg=",
        "fingerprint": {
          "rawId": 478591023,
          "currentIndex": 1,
          "deviceIndexes": [
            0,
            1
          ]
        },
        "timestamp": "1661776696529"
      },
      "AAAAACDb": {
        "keyData": "6EsTYfXc8+hcHopWL2gU8b/28UD9lHqwvKk2AZ9XXaI=",
        "fingerprint": {
          "rawId": 478591022,
          "currentIndex": 1,
          "deviceIndexes": [
            0,
            1
          ]
        },
        "timestamp": "0"
      },
      "AAAAACDc": {
        "keyData": "MOZlhF8EMcx/sLkPjEBPufOi5OnqRyYKikv1AGdw8KA=",
        "fingerprint": {
          "rawId": 478591022,
          "currentIndex": 3,
          "deviceIndexes": [
            0,
            1,
            3
          ]
        },
        "timestamp": "1661720275350"
      }
    },
    "senderKeys": {
      "491788880008-1584463053@g.us::447935699967::0": [
        {
          "senderKeyId": 1728855556,
          "senderChainKey": {
            "iteration": 144,
            "seed": "oWm/DHki+56lU0b5dlR0/F30xE7GWpcNqQF+eDEE6Qk="
          },
          "senderSigningKey": {
            "public": "BWtJbjorKPU3jsX9Q1tkt3SnBGA2uNbf6TIlxZ7dbN8w"
          },
          "senderMessageKeys": []
        }
      ],
      "491788880008-1584463053@g.us::4915678244172:15::0": [
        {
          "senderKeyId": 1232724009,
          "senderChainKey": {
            "iteration": 9,
            "seed": "5viN0WVibQLfP4ga+6VTExaVdU8/ZrtH0Q/eKPanJm0="
          },
          "senderSigningKey": {
            "public": "BSUQhM0cgwT1acslLih/JMLcEVGAAHCg/19w/mWBEnx7",
            "private": "8HwsVa9cmaD67jH1e8FfEGVslXYW28oys7RbAyDSCXM="
          },
          "senderMessageKeys": []
        }
      ],
      "status@broadcast::4915678444438::0": [
        {
          "senderKeyId": 1814125544,
          "senderChainKey": {
            "iteration": 5,
            "seed": "MzB0UOENACb7rtTzFB8wP03tuHiHOQM9K3ZiyW5kHdk="
          },
          "senderSigningKey": {
            "public": "BUImELZC2oTHf3PFiahlooF6uXeWeK/CPEsOfLt+JQAt"
          }
        }
      ]
    },
    "senderKeyMemory": {
      "491788880008-1584463053@g.us": {
        "4915678244172@s.whatsapp.net": true,
        "4915678244172:14@s.whatsapp.net": true,
        "4915256334479@s.whatsapp.net": true,
        "447935699967@s.whatsapp.net": true
      }
    },
    "appStateVersions": {
      "critical_unblock_low": {
        "version": 23,
        "hash": {
          "type": "Buffer",
          "data": "3EJf5MwELV54usIB0GNLQZW/z/uGpEvTeGz8uUqZcfhGYfvtLYcMg1dZ354PqsynuZ6Q5mtvcB90bvYdiLD/hKNTRxjwHPMFFTzJkUgbZuG6wWDhpnxEPMksQabF9k7gqynOgje61HOFFz+5Az/cARyz6pGCiREgL98sJmMWMnU="
        },
        "indexValueMap": {
          "BAAL4269IDbXoNHHJi2RzBfNjoD2q757xKZlr1YcF/s=": {
            "valueMac": {
              "type": "Buffer",
              "data": "QtAv/sbZmjtTwrszlntCK5n6rzjacpBO5YsKsu0b1/8="
            }
          },
          "H1SAUuK+UmG2WmnLxsXFsQVrIuqUb14tWAJZyoXzy7g=": {
            "valueMac": {
              "type": "Buffer",
              "data": "xvkbI/o6hrOdISNGU4tRzpBm9xf00/5PHwbFokTwTUg="
            }
          },
          "KPqejDxF3bZUIS47zCcuy3sthCAwa7NxP8tV0sO/bIk=": {
            "valueMac": {
              "type": "Buffer",
              "data": "FrpFZu8R+kLzSCH55E2L5pB8Y/6zJXdRvG7JbIhXLs0="
            }
          },
          "Lr85uiA9avVthtE5SJ/7l63jlItRiMNE7knkfOT0T0s=": {
            "valueMac": {
              "type": "Buffer",
              "data": "sTQpsOTrsINlS2TsZH5Q7jKEHNvAT5YwWkaA3Vgo2Vg="
            }
          },
          "MENKhNsB+PyMXABkSEcXbeHyoFvID6l9oXHgNbxUbe8=": {
            "valueMac": {
              "type": "Buffer",
              "data": "VSazWws+GwP35nfiDIqN7oHHKHo3CZWev/l6lR+vmRc="
            }
          },
          "PHIF65yp2ypBUUXdWkbcOs0z7dOj5hn740Y/f1m/+84=": {
            "valueMac": {
              "type": "Buffer",
              "data": "5V9Zo5pAX2hyA42pU1Gvaa8mv6TeSOdxAUUob42A4fI="
            }
          },
          "QUWTR5FbT5JGPFDPiqSmqcYqM5OLOTWNcqjRNWosIZc=": {
            "valueMac": {
              "type": "Buffer",
              "data": "xcJAds2qU+qfzdKfk4VTBIsywZP9Yz2dISFC074kt7w="
            }
          },
          "RQ1wV9h4uYyThfJ3HgmiC0WWhMp7FQeRrAFIDpe7B+A=": {
            "valueMac": {
              "type": "Buffer",
              "data": "UphuXGx0p9ufFRg3QPiFju9+dGuYWsShK1Rr22BCtV8="
            }
          },
          "RgdciQF40lQK8VudRoeyS6iFDCDbvIln7LJ0Qdzw+No=": {
            "valueMac": {
              "type": "Buffer",
              "data": "LNDOejXTjfz9MxesjiI8kHua9kljXwcJffZlFdR79Qo="
            }
          },
          "WrI4xqtQA5t7WfK/OrQ7qu8fGv+WY+7WujAI0RSLims=": {
            "valueMac": {
              "type": "Buffer",
              "data": "zm9ZNvlL7M1hMQPy4K+5+RVYYoF4UL9C80JMOtzm8cY="
            }
          },
          "Xv9/M+GOWGNh/FMI/ZPpq6DfyFmB0TaVPReO3HMeXCA=": {
            "valueMac": {
              "type": "Buffer",
              "data": "2RlDM+WnpgFG5sTYXG2JPa8BYBz0rm1/zhOI0yyf05I="
            }
          },
          "YhYgBgcQTTpHIQujoXUlfvrGhIQ/IZCLd7jOKiWA9Ag=": {
            "valueMac": {
              "type": "Buffer",
              "data": "Vb41ImQjuTLsK72RssMeCOe/VIb0jU+n+M9b/2bJjPM="
            }
          },
          "bj0wO+QUr+lGrdgm2o+yII8c2jl5Wk4i6Cex4R7nHFQ=": {
            "valueMac": {
              "type": "Buffer",
              "data": "1j4RK0t9n3csgq29cQQ1iTVDq1V0o72gXW4ElR47+y0="
            }
          },
          "ezBK/uSchkOw493wguBO7RnO1PdPxsRtOLRDKjNhH/8=": {
            "valueMac": {
              "type": "Buffer",
              "data": "qdXgsBhBwGkzuGWxCQS6WwA0J39F4SfPfAHouh9A65I="
            }
          },
          "huDqGi4HrHXQGf+hJEd3SUOyWkD5jT5GEjIAdMTifRA=": {
            "valueMac": {
              "type": "Buffer",
              "data": "u7w+ZlAZGhAoMlWz2BEIC+WWbBS0NBqKDRqTyVfpuWc="
            }
          },
          "jD0jigl5QwETP740OUWQvOHztCmBf6T114hcUdiNmYU=": {
            "valueMac": {
              "type": "Buffer",
              "data": "R21SywM1nMDPxwZ/zVZzp1qxel9OKCnQ3rg+2nzkoHs="
            }
          },
          "jSSl8+/5f9iuAdouaVjpxK1TsowsVcdN6boCDFZ7pms=": {
            "valueMac": {
              "type": "Buffer",
              "data": "veyOcvM4Jr0zEJu6pJH2HmbPLCMkjMJwz1t6bC8dBlc="
            }
          },
          "jiix7uqud3anNo+F3V0KJGbFTNyDZ22n5qtEdrLIF1I=": {
            "valueMac": {
              "type": "Buffer",
              "data": "NzXNpu/f//rNrPz5Y6TGw9uFOPljOGR6SCDb+mXZAog="
            }
          },
          "khimuKbOk4w1CffOeUXRgY94Get/eYh7/Xe4CH3CCuM=": {
            "valueMac": {
              "type": "Buffer",
              "data": "aRxoOcYeowwAvR7JbheAwhUgL6DvqWX4gN4mfZywwLI="
            }
          },
          "mmYrLus9f9efi2XPQHL2+EUs9EnwwEQE9XnH7w9I7tw=": {
            "valueMac": {
              "type": "Buffer",
              "data": "i2sjCZTqsWxWoetljsrz86+IKvsy/9GiomCIX2lMQ3g="
            }
          },
          "n7BhO7SHErkWKs3d3px9ynV0+tIEpeSpokEpGkXVnUw=": {
            "valueMac": {
              "type": "Buffer",
              "data": "jvH0PjXlr6X+iOVLAWKxAd3VeloMOjZDo9hTxLmB2/s="
            }
          },
          "tfBBJBGUM2U0gj07R48YO8K8f82OPgPKrqXC/iZItd4=": {
            "valueMac": {
              "type": "Buffer",
              "data": "40w4YXtWYHy1IZmZY0owlQaZdF1F7x6m4fvwcfgaNPU="
            }
          },
          "uzLpbvjq3VnPzjXnJQ/o0+0AIb50YTrznS1a2b1HZxQ=": {
            "valueMac": {
              "type": "Buffer",
              "data": "qri4HInkYSqxZC+c1WDZ5wTGjjYuqWNr1dOkx2k9JIM="
            }
          },
          "z51ewcRL382kJIcNOKIRePbytEuNSMBOXDGoHlbNUEY=": {
            "valueMac": {
              "type": "Buffer",
              "data": "u6VlrxoPYY+8KI99wPHAoNN0JewL5q2tywDw34flv5o="
            }
          },
          "0G3pMH2k8jUpAck7zWa0X0I7ZjUK3uG9IfXpJl8+DAM=": {
            "valueMac": {
              "type": "Buffer",
              "data": "uiSzqI1rFBWHNqnCszMOrFZQv6neLFwwPQz/qRseKA0="
            }
          },
          "3eCuPmach5NXNk0VZi/+dG2L1e20ZAs1b7rFaTyUpkA=": {
            "valueMac": {
              "type": "Buffer",
              "data": "FbWarl020qe2ZAJQwCXndwQ6XoDpkyXyiAM0eDPW2+g="
            }
          },
          "95FcmArvDF7+uNMnSPj346aUOBBtcC3rAZtlgLrBGDc=": {
            "valueMac": {
              "type": "Buffer",
              "data": "nIdShzwEf/Y3S569M98if1iUGF1r6nys59FcWnEyedY="
            }
          },
          "UVeXziITaY9zvL8y6YQeeTnA+ClI8ZkB9Z61iiTO6pA=": {
            "valueMac": {
              "type": "Buffer",
              "data": "/UCA+WjsiHf3WAyZOQtcQxZv+HVbgKq2ZHew9aSUEbQ="
            }
          },
          "tptwcyeSLdJeFbOazE8swT/dISyNl+uwVk8bfQoljIg=": {
            "valueMac": {
              "type": "Buffer",
              "data": "YBESR/AXSx29MNt1gDumw6InwLV9Y9tOzmZwmC52wvo="
            }
          },
          "jB550UvqaRvVH7uRYGqosYrU4LPc4Iiy1H1kciD8G/8=": {
            "valueMac": {
              "type": "Buffer",
              "data": "7OiRtZIqAPqRPFVr5f0VXpge6XBR0vlRiUe0KKdJJ18="
            }
          },
          "hopaJyEZyowNvYmcz1FAN37dxGuhSp+ZxoRa8nQOCE4=": {
            "valueMac": {
              "type": "Buffer",
              "data": "BXV69BVHniCcE1BRcWuHw5va+j457/jilbNVqRwv8HU="
            }
          },
          "qSaMEKCNcUUyPAsW1rBtQ2j3y1sVRdLH8zs16oy82mQ=": {
            "valueMac": {
              "type": "Buffer",
              "data": "dNrOZq+nMRItLpNKwO4gdxSojrMKTBR4TV4LE/qW+LY="
            }
          },
          "MsXbvwwsj0zHoho7r5F8Y66+vPf8JujQrUyosDil05Q=": {
            "valueMac": {
              "type": "Buffer",
              "data": "g7+zLiCXoTi5kzcybYxeqUKMS88WF7O6ndFhBoVi5ec="
            }
          },
          "PLjtAycbfh+7W57qKZP/Ybn7wO69NatQYpRNmf4cof8=": {
            "valueMac": {
              "type": "Buffer",
              "data": "6iEw0nnyugf+LhsZwAIM55nPRy9zA5JyH4qYUp20wVs="
            }
          },
          "t1Qb5MK47n3hj8+zjQi4JfLJhctEzlNSXORMaaYAtRY=": {
            "valueMac": {
              "type": "Buffer",
              "data": "BhEoEGIagEmZ7fMGRA/uVUBS5A7WbOJMmcLNSE4OO/Q="
            }
          },
          "HNxrJr7uvC7bcCNMAZmW7ptaVgPXPVvfWHBQ9uE2Uio=": {
            "valueMac": {
              "type": "Buffer",
              "data": "WqtpZHogErIVlG4C6+rTRXcQRYpmOd+0toVbNIxWEeU="
            }
          },
          "zmg6oAvM6gMTdRHChQUE/MWnCskwI5haet4kGn8TH8M=": {
            "valueMac": {
              "type": "Buffer",
              "data": "2DSE7EGW08MybJtHvz4YoN7iWCVIeNWIKkkVFskZsXE="
            }
          },
          "kuuEZs/+31sDFEwuGlPQ6q9XMLBEbHl+vG+9qAmCtA4=": {
            "valueMac": {
              "type": "Buffer",
              "data": "93XuT8Hyms0yv+Ukg1wNkQCFEqjpNfjTpNs76EU741E="
            }
          },
          "ig/DSuAzffkUQozCZ1ri6cGISSc66Xne3i5Err1J9wI=": {
            "valueMac": {
              "type": "Buffer",
              "data": "GYBb4u8FuvteKLWuR0VMeyuDZ0SxNcNkAOR62D2kdSk="
            }
          },
          "qeCdv5Sj6F+W9zbA1WIiULUhJK9I766UXeZW6XQVfwc=": {
            "valueMac": {
              "type": "Buffer",
              "data": "km8RLj1/Mf3W8Gnl1YpMG8BzUc1ZMY4bnfZpvTebcUc="
            }
          },
          "Q9cBpgvo48nyVRMgFSJegftpbkOPFcx5dro9UtAUbsk=": {
            "valueMac": {
              "type": "Buffer",
              "data": "gbs//aZRT7RJdqhwsjE+IsPVdtjxon8LjNrtfLU0c98="
            }
          },
          "hCSQj5ANalm8NsGMe2knQX0b3KijyjJfQrAxYnipCx4=": {
            "valueMac": {
              "type": "Buffer",
              "data": "9lMuYZ9RgD5+mpT+v6+GsfP9ye8sSK/ruKexywxNAvw="
            }
          },
          "zIc48dUIc1lJFOtXFV0vd/nxx2emX2SAceOT/yCDo/M=": {
            "valueMac": {
              "type": "Buffer",
              "data": "Wg1AqKG+IzTjg7nSd/t7fJtsKTPbXNJgyAEamyWMVjU="
            }
          },
          "yvXXoNK94V2dLWpDepE0AYQQc9TNs+Fll+C8MfKMCig=": {
            "valueMac": {
              "type": "Buffer",
              "data": "Ffv6Ce0nAWq0H0FdhfCOXxQd6dd+hFYtXyat6gkh1o4="
            }
          },
          "I4oeFGlxxhmrUSGTZlD22LaDxPl0o3WrTnD6QrLngVg=": {
            "valueMac": {
              "type": "Buffer",
              "data": "8e7yEcTZlimbBT7DDoI9OoWaX5YiEqmCfz+8aDDKDTI="
            }
          },
          "kDt/JmNI4KJU1T8dPY5NJ0cx9U83IJKnAku0F4lRWuk=": {
            "valueMac": {
              "type": "Buffer",
              "data": "7/EB5oQYJt4EG1+nDtzjuteq3XT1EczDmtRKjiZ19Co="
            }
          },
          "RRdTveW97NJ/MxeS+BlpKahYf40X+nnD+50KZ9eCF4k=": {
            "valueMac": {
              "type": "Buffer",
              "data": "piaUCimj8Bwn9SEr2lUF2DV3SpHLoujas1k3N73EEYI="
            }
          },
          "+5K6qAovJGqRwUdh4uXFj9ouGtkS+Wx9vzyqkG45dGA=": {
            "valueMac": {
              "type": "Buffer",
              "data": "GWb3sZYNbN7OCqRIZLH3sr1u+eIeJonGIUDhCmtBkd0="
            }
          },
          "aFcA/8U21dBQFmfy0XN+r6ioZTOLLTHmIELuszV0u60=": {
            "valueMac": {
              "type": "Buffer",
              "data": "tMkvqM06LmJy0dGFp8jZAYKwzYuqM4gYJ12Fqgy8CQg="
            }
          },
          "HesUc9T+wMag3KiXBa4+/taf1QBzN1W6RHiqExRXAAU=": {
            "valueMac": {
              "type": "Buffer",
              "data": "vdHj7WDxYsSW0KcwSH+RzvxuGM6g+y7pxeslY/EZch8="
            }
          },
          "EH+/xzXUWcmc7rlyGSV4p7OBGaBSLnqEpO+TlMBc7yY=": {
            "valueMac": {
              "type": "Buffer",
              "data": "GAE5Wgs6eEbMRjb8C3Urqw5OHQOXK9ZdXVBZdaaI1Fg="
            }
          },
          "8i90B3k6WZmJNrjpLXHJt4fgc2GSM4v0u07OZbYUNd0=": {
            "valueMac": {
              "type": "Buffer",
              "data": "mU8DvL7puJvbNihwBKU8+q9hUAJP+TXWNM1Pw3uaqKY="
            }
          },
          "sPL0WbMx/+waThv4H3VBZCGz2GC9n5yHfaz+w16IFTc=": {
            "valueMac": {
              "type": "Buffer",
              "data": "NA4/Y4xnEA/2V0kx+vdugQ5UEpEhZhvsCg+JlenSsJo="
            }
          },
          "J+lOT18OVFdqQt60C9mG6xy6nwZdvIS49y2vNCHnWyo=": {
            "valueMac": {
              "type": "Buffer",
              "data": "i9OQibZq+U58Q/1HO+PPANm+zmZNiI3Dg5GjaJicFhE="
            }
          },
          "f7jLJS5O6O/gSSu6F/iMDAcKzSbOw09KucTQFYBX7ws=": {
            "valueMac": {
              "type": "Buffer",
              "data": "h0KuP28aoJpvcL/eLJ8UtiEim9K5wYIdAJWjDqa5zF4="
            }
          },
          "es1C0ocxeEe/7YC4ueXmyuYe0fnn4zRd7/P9ftmgLeQ=": {
            "valueMac": {
              "type": "Buffer",
              "data": "G9sCcGxWPoatGqudDRWgXjT65sOSt6zo7XRG9QZLSos="
            }
          },
          "78qHtJpkxwHZfJbyZ5D17NamaM6GZdQhptPVX3q6SQY=": {
            "valueMac": {
              "type": "Buffer",
              "data": "naZupBcDeYat176XanBw9C27PFRaky9K0+LsBQKlqdg="
            }
          },
          "LlcoP+4mOYbxto1KpuLCnwgRE5wz8idQp9iJ9PPRRKo=": {
            "valueMac": {
              "type": "Buffer",
              "data": "q6YyX/p6Uo2DkDQbkWc4ZqtFV9D8qRjSUozYeqFsE0E="
            }
          },
          "RoQVMtSWIU3Ivgcu9zHSg0zb8J4AKDGpwU0EtHb0RnA=": {
            "valueMac": {
              "type": "Buffer",
              "data": "SwGOVXWRYj+qUeDj7wAyuqpwHnHDU+ldakjcTJ2hKNg="
            }
          },
          "qK3vMWRBO7vnplu13TXUZEt3z5tz64d5RUzg7/vdKKU=": {
            "valueMac": {
              "type": "Buffer",
              "data": "dNqXWoozGebaFdE08Vd/nuKMwZc+wK/7NLP2AImhg1U="
            }
          },
          "thzMDvQWGFkpFLoYEi+YeAOx1kXMEEHghtly7SwLISs=": {
            "valueMac": {
              "type": "Buffer",
              "data": "rm/OoQ7KtPuFsNF7wLvT36KEf+IMeGygHI5Mg+EbSQU="
            }
          },
          "qmzTPlztZp37EFYoFE7BJEMS+JL9WewRBvKuPOBmpyc=": {
            "valueMac": {
              "type": "Buffer",
              "data": "BSAlYQDaQ5mZpEzOVsAT6gDNquK62b0adZCYWZ8WEuM="
            }
          },
          "4MrHKuFMYuoqekD9gcO0ZnE/7xf14dET9uH71HFqlJQ=": {
            "valueMac": {
              "type": "Buffer",
              "data": "LLOiLELoUFMygvbS5sdJJyVuwDjjODEpcUsU/LwGiyE="
            }
          },
          "unH57QhFNjSGwTtihqJ/wCJSwIQpfq99Z7pH9LqNb5o=": {
            "valueMac": {
              "type": "Buffer",
              "data": "oB6nWyATWOdLz36tfJ9AVwhbBDTZgpNu6rk366IHBZc="
            }
          },
          "YXWOebbr7BIKhGIKlpm8AGPtlHNyX9ghwIgqMTdgLdk=": {
            "valueMac": {
              "type": "Buffer",
              "data": "YuGd18syylMBE1QLWX9M21hDYo/9Lw9RM44U7ZHTmOQ="
            }
          },
          "AfdRbHqplILeKH6KBmXVF8pT0qDrCjnNYBG9/i7BjoA=": {
            "valueMac": {
              "type": "Buffer",
              "data": "CmVOmwwboMBjboRPC+06C7Bz4E5rZvdrkrbPJjwPuY8="
            }
          },
          "6Ax/psQW9H6XK0VPSWZ9YX+KwcDLLwj0XD/7jh9fvYg=": {
            "valueMac": {
              "type": "Buffer",
              "data": "1GqQcsHcadlpFlB4iaLk0Q30S/TwkIU7/ETJ2ns+xEs="
            }
          },
          "t69NwjrG5GY3CPaii6SPXsyoMcj9PhmnEjU4UAok70Y=": {
            "valueMac": {
              "type": "Buffer",
              "data": "Cse1fsYYKN/nM2VhMe/w/GqDnn/2avntC72nbfcqnuk="
            }
          }
        }
      },
      "regular_low": {
        "version": 23,
        "hash": {
          "type": "Buffer",
          "data": "1fX6vT13y4znpuCyn3L7Elj0RI+hHn00M77qB7G3TWUf3jizp1Pq07eg39j53UDajritiUvYwaPoSfVSclHIVg4cUsEy85Ems114SY86B49p9ggpQd95IpQP138SE4+tlRiNP1yoVa4Y+pOu3TMzQCOB/NuyZkCRfFUhQ3uhGyo="
        },
        "indexValueMap": {
          "q/sfKwlNVXf6WSEZdOtO9KQfxgtlckv2+tGiUWIx6kw=": {
            "valueMac": {
              "type": "Buffer",
              "data": "v4GO/2b8XTJ1mvmiOxxGvC5e5cze0nEQB81sGFpoJSY="
            }
          },
          "5uC9Ggi9scc0kOX9oHeHZAqSfTT+V0gOBsFm+r2wOdw=": {
            "valueMac": {
              "type": "Buffer",
              "data": "O86niS/rua9UfdyVMxJpNYPZVzpW8faDGnMkZiABiy4="
            }
          },
          "Ew6KWCbIfYjjaLRAklKe1+LtO2ZDYyYdK07vpIKoqWY=": {
            "valueMac": {
              "type": "Buffer",
              "data": "IdZdFzMJp4KXy8E8cNDpuoWx57QcSRYuPPslfG34l2I="
            }
          },
          "KS/N5R0MoC05CFx2mBOjrmZXMBHuAOXcGSFPdE89IgY=": {
            "valueMac": {
              "type": "Buffer",
              "data": "5S4rOGxkQfwg41DYA3EoBY36h/CCWAuNG6e4H0mmjDo="
            }
          },
          "Baobg7n9mffQ/gRxlpRH1Vr729E7RVIh40/txa7QwNU=": {
            "valueMac": {
              "type": "Buffer",
              "data": "QW6KwLdm1FrDAIAS6xhb0lfMgL0blBcQG+2LZjpCk5o="
            }
          },
          "KdxeWPgcH+LED9K8fTsSG2erV42FMPKFKIC1MnJuyDE=": {
            "valueMac": {
              "type": "Buffer",
              "data": "BGBWI0HJq88YYogIn6QYDUeGGkZhhmMO3hDoievnu18="
            }
          }
        }
      },
      "critical_block": {
        "version": 14,
        "hash": {
          "type": "Buffer",
          "data": "wkxRyq47knlkcuD8MYQHK9KAuMb1ylEVqZT7K8edwh+aG7hAQ6aBMePXvfwgnSZ3y1w+SUc1R4ODgO7+gDpBLhJs9g2yX4zFX0sh+g7peK6R25Ui/IjfQ0A8LN2jEyG2BRlMfy/xbeBjHSvhurS+nafvA6EDBu+5fMPEBMkmwN0="
        },
        "indexValueMap": {
          "Hxik/tXa08wIuOptESxf/UPeltPNsI6F1XCQORsjF1Y=": {
            "valueMac": {
              "type": "Buffer",
              "data": "53+noyjoq/PEIL8iPtFVU37DqPNXSohkyk/zmkTEiUA="
            }
          },
          "BsP8/OrEP7e8BozpwODql96rZTxpXTcyRBMIamyLS10=": {
            "valueMac": {
              "type": "Buffer",
              "data": "FswLsAXy4gqSzsFgc6++dhdxyE/Ox/GqZJEWAQdO7wg="
            }
          },
          "3HaNFaALhn2qCgUsFBI4bf7MVngxF8Kwl7gFujMVLg4=": {
            "valueMac": {
              "type": "Buffer",
              "data": "Tglgg3KORg3oKtFA9P3wwFMeUEtpNka31xX/l2h7XRw="
            }
          }
        }
      },
      "regular_high": {
        "version": 14,
        "hash": {
          "type": "Buffer",
          "data": "Y/O9qzeKQl15qNt2J8XKVZflp3EMehXtNopR9gUEB5FHQpM92nX7D/C7RQdej8t+gYbmLuV2gL1d9Q22oLNVg9CWEbWc/XK+EgF7jiX//JRoTbx61LPm1JizUgixj3yL6p0hQy0eaSBwgdZiUU7PeJ00M292Rlx8ZARkaZ5lJaY="
        },
        "indexValueMap": {
          "hSdlDdFVAOJ6mNtDBroHSYY4/UNEZM66BpYFYRrMTwE=": {
            "valueMac": {
              "type": "Buffer",
              "data": "+QEjHHRs9G5g/+CYr9Ap6WKsQR+MQumZel4f6pb8utQ="
            }
          },
          "nNDYlnNO0uOhCxajQyQKxGxCD9yneVqng0IB75opgJo=": {
            "valueMac": {
              "type": "Buffer",
              "data": "gW3GYi/gRRKKV3WoEQ/saS+xFGpiwLxgLQ2Cl3kI4pY="
            }
          },
          "XFCJ+kSKTvDl588h8bU+q6JHa6q3Bn4+cCHKdc4u4do=": {
            "valueMac": {
              "type": "Buffer",
              "data": "Ua8xr5ePzurJ0bdB0V7DC10zkTJMtAgR5/L6LeKHA2s="
            }
          }
        }
      },
      "regular": {
        "version": 13,
        "hash": {
          "type": "Buffer",
          "data": "i1FrbB84luEDHEq/k0CP/iZ3dyofkkRICxV6omnMJeancWhpglt9P1Ss5on7Jdx/uULT5Fs/9Xwz6nLypriphN5QAWGWMgUw6D/cQ56StItY9d0/FMtIssgqYbAnhiULwchbyzhz4cXzBf/ULbjlLnccpiznLUS6Jk11o7+tcGs="
        },
        "indexValueMap": {
          "84lPJ5c/oaWI0IpexdmRMcO6yM3xHDHqlFP5ilRITH8=": {
            "valueMac": {
              "type": "Buffer",
              "data": "sUTOmxukG7LIuy6kOLTczmgPHC+vugVtUYTATDdRuiU="
            }
          },
          "mWQD85ESXGrRVeZsySEWR7UTOs8NKmg8T9zOkzx36GM=": {
            "valueMac": {
              "type": "Buffer",
              "data": "f5CRJYCde7yfnyYIiUpt2Xxg4ezn4ROfaOsPkB9HT7c="
            }
          }
        }
      }
    }
  }
}